hostdb/__init__.py
hostdb/exceptions.py
hostdb/hostdb.py
hostdb/inventory.py
hostdb/manifest.py
hostdb/naming.py
hostdb/py.typed
hostdb/validation.py
hostdb/resources/wordlist
hostdb/yaml_loaders/__init__.py
hostdb-2.1.0.dist-info/LICENSE
hostdb-2.1.0.dist-info/METADATA
hostdb-2.1.0.dist-info/WHEEL
hostdb-2.1.0.dist-info/entry_points.txt
hostdb-2.1.0.dist-info/top_level.txt
hostdb-2.1.0.dist-info/RECORD
