Metadata-Version: 2.1
Name: hostdb
Version: 2.1.0
Summary: Hostdb manages homelab hosts using infrastructure as code principles.
Home-page: https://github.com/allenporter/hostdb
Author: Allen Porter
Author-email: allen.porter@gmail.com
License: Apache-2.0
Classifier: License :: OSI Approved :: Apache Software License
Classifier: Programming Language :: Python :: 3
Classifier: Programming Language :: Python :: 3 :: Only
Requires-Python: >=3.10
License-File: LICENSE
Requires-Dist: ansible >=7.1.0
Requires-Dist: mashumaro[yaml] >=3.11
